odoo/addons/sale_stock_reservation_issue_on_qty_at_date_widget/README.rst
odoo/addons/sale_stock_reservation_issue_on_qty_at_date_widget/__init__.py
odoo/addons/sale_stock_reservation_issue_on_qty_at_date_widget/__manifest__.py
odoo/addons/sale_stock_reservation_issue_on_qty_at_date_widget/i18n/sale_stock_reservation_issue_on_qty_at_date_widget.pot
odoo/addons/sale_stock_reservation_issue_on_qty_at_date_widget/readme/CONTEXT.md
odoo/addons/sale_stock_reservation_issue_on_qty_at_date_widget/readme/CONTRIBUTORS.md
odoo/addons/sale_stock_reservation_issue_on_qty_at_date_widget/readme/DESCRIPTION.md
odoo/addons/sale_stock_reservation_issue_on_qty_at_date_widget/readme/INSTALL.md
odoo/addons/sale_stock_reservation_issue_on_qty_at_date_widget/readme/USAGE.md
odoo/addons/sale_stock_reservation_issue_on_qty_at_date_widget/static/description/icon.png
odoo/addons/sale_stock_reservation_issue_on_qty_at_date_widget/static/description/index.html
odoo/addons/sale_stock_reservation_issue_on_qty_at_date_widget/static/description/reservation_issue_color.png
odoo/addons/sale_stock_reservation_issue_on_qty_at_date_widget/static/src/widgets/qty_at_date_widget.esm.js
odoo/addons/sale_stock_reservation_issue_on_qty_at_date_widget/static/src/widgets/qty_at_date_widget.xml
odoo_addon_sale_stock_reservation_issue_on_qty_at_date_widget-16.0.1.0.0.2.dist-info/METADATA
odoo_addon_sale_stock_reservation_issue_on_qty_at_date_widget-16.0.1.0.0.2.dist-info/WHEEL
odoo_addon_sale_stock_reservation_issue_on_qty_at_date_widget-16.0.1.0.0.2.dist-info/top_level.txt
odoo_addon_sale_stock_reservation_issue_on_qty_at_date_widget-16.0.1.0.0.2.dist-info/RECORD
